{"textures":[{"image":"181.png","format":"RGBA8888","size":{"w":512,"h":1598},"scale":1,"frames":[{"filename":"0015.png","rotated":false,"trimmed":true,"sourceSize":{"w":98,"h":95},"spriteSourceSize":{"x":0,"y":0,"w":90,"h":95},"frame":{"x":0,"y":0,"w":90,"h":95}},{"filename":"0016.png","rotated":false,"trimmed":true,"sourceSize":{"w":98,"h":95},"spriteSourceSize":{"x":0,"y":0,"w":90,"h":95},"frame":{"x":90,"y":0,"w":90,"h":95}},{"filename":"0019.png","rotated":false,"trimmed":true,"sourceSize":{"w":98,"h":95},"spriteSourceSize":{"x":0,"y":0,"w":90,"h":95},"frame":{"x":180,"y":0,"w":90,"h":95}},{"filename":"0020.png","rotated":false,"trimmed":true,"sourceSize":{"w":98,"h":95},"spriteSourceSize":{"x":0,"y":0,"w":90,"h":95},"frame":{"x":270,"y":0,"w":90,"h":95}},{"filename":"0035.png","rotated":false,"trimmed":true,"sourceSize":{"w":98,"h":95},"spriteSourceSize":{"x":0,"y":0,"w":90,"h":95},"frame":{"x":360,"y":0,"w":90,"h":95}},{"filename":"0036.png","rotated":false,"trimmed":true,"sourceSize":{"w":98,"h":95},"spriteSourceSize":{"x":0,"y":0,"w":90,"h":95},"frame":{"x":0,"y":95,"w":90,"h":95}},{"filename":"0039.png","rotated":false,"trimmed":true,"sourceSize":{"w":98,"h":95},"spriteSourceSize":{"x":0,"y":0,"w":90,"h":95},"frame":{"x":90,"y":95,"w":90,"h":95}},{"filename":"0040.png","rotated":false,"trimmed":true,"sourceSize":{"w":98,"h":95},"spriteSourceSize":{"x":0,"y":0,"w":90,"h":95},"frame":{"x":180,"y":95,"w":90,"h":95}},{"filename":"0003.png","rotated":false,"trimmed":true,"sourceSize":{"w":98,"h":95},"spriteSourceSize":{"x":3,"y":0,"w":89,"h":95},"frame":{"x":270,"y":95,"w":89,"h":95}},{"filename":"0004.png","rotated":false,"trimmed":true,"sourceSize":{"w":98,"h":95},"spriteSourceSize":{"x":3,"y":0,"w":89,"h":95},"frame":{"x":359,"y":95,"w":89,"h":95}},{"filename":"0011.png","rotated":false,"trimmed":true,"sourceSize":{"w":98,"h":95},"spriteSourceSize":{"x":3,"y":0,"w":89,"h":95},"frame":{"x":0,"y":190,"w":89,"h":95}},{"filename":"0012.png","rotated":false,"trimmed":true,"sourceSize":{"w":98,"h":95},"spriteSourceSize":{"x":3,"y":0,"w":89,"h":95},"frame":{"x":89,"y":190,"w":89,"h":95}},{"filename":"0023.png","rotated":false,"trimmed":true,"sourceSize":{"w":98,"h":95},"spriteSourceSize":{"x":3,"y":0,"w":89,"h":95},"frame":{"x":178,"y":190,"w":89,"h":95}},{"filename":"0024.png","rotated":false,"trimmed":true,"sourceSize":{"w":98,"h":95},"spriteSourceSize":{"x":3,"y":0,"w":89,"h":95},"frame":{"x":267,"y":190,"w":89,"h":95}},{"filename":"0031.png","rotated":false,"trimmed":true,"sourceSize":{"w":98,"h":95},"spriteSourceSize":{"x":3,"y":0,"w":89,"h":95},"frame":{"x":356,"y":190,"w":89,"h":95}},{"filename":"0032.png","rotated":false,"trimmed":true,"sourceSize":{"w":98,"h":95},"spriteSourceSize":{"x":3,"y":0,"w":89,"h":95},"frame":{"x":0,"y":285,"w":89,"h":95}},{"filename":"0001.png","rotated":false,"trimmed":true,"sourceSize":{"w":98,"h":95},"spriteSourceSize":{"x":2,"y":0,"w":88,"h":95},"frame":{"x":89,"y":285,"w":88,"h":95}},{"filename":"0002.png","rotated":false,"trimmed":true,"sourceSize":{"w":98,"h":95},"spriteSourceSize":{"x":2,"y":0,"w":88,"h":95},"frame":{"x":177,"y":285,"w":88,"h":95}},{"filename":"0013.png","rotated":false,"trimmed":true,"sourceSize":{"w":98,"h":95},"spriteSourceSize":{"x":2,"y":0,"w":88,"h":95},"frame":{"x":265,"y":285,"w":88,"h":95}},{"filename":"0014.png","rotated":false,"trimmed":true,"sourceSize":{"w":98,"h":95},"spriteSourceSize":{"x":2,"y":0,"w":88,"h":95},"frame":{"x":353,"y":285,"w":88,"h":95}},{"filename":"0021.png","rotated":false,"trimmed":true,"sourceSize":{"w":98,"h":95},"spriteSourceSize":{"x":2,"y":0,"w":88,"h":95},"frame":{"x":0,"y":380,"w":88,"h":95}},{"filename":"0022.png","rotated":false,"trimmed":true,"sourceSize":{"w":98,"h":95},"spriteSourceSize":{"x":2,"y":0,"w":88,"h":95},"frame":{"x":88,"y":380,"w":88,"h":95}},{"filename":"0033.png","rotated":false,"trimmed":true,"sourceSize":{"w":98,"h":95},"spriteSourceSize":{"x":2,"y":0,"w":88,"h":95},"frame":{"x":176,"y":380,"w":88,"h":95}},{"filename":"0034.png","rotated":false,"trimmed":true,"sourceSize":{"w":98,"h":95},"spriteSourceSize":{"x":2,"y":0,"w":88,"h":95},"frame":{"x":264,"y":380,"w":88,"h":95}},{"filename":"0041.png","rotated":false,"trimmed":true,"sourceSize":{"w":98,"h":95},"spriteSourceSize":{"x":2,"y":0,"w":88,"h":95},"frame":{"x":352,"y":380,"w":88,"h":95}},{"filename":"0042.png","rotated":false,"trimmed":true,"sourceSize":{"w":98,"h":95},"spriteSourceSize":{"x":2,"y":0,"w":88,"h":95},"frame":{"x":0,"y":475,"w":88,"h":95}},{"filename":"0043.png","rotated":false,"trimmed":true,"sourceSize":{"w":98,"h":95},"spriteSourceSize":{"x":2,"y":0,"w":88,"h":95},"frame":{"x":88,"y":475,"w":88,"h":95}},{"filename":"0044.png","rotated":false,"trimmed":true,"sourceSize":{"w":98,"h":95},"spriteSourceSize":{"x":2,"y":0,"w":88,"h":95},"frame":{"x":176,"y":475,"w":88,"h":95}},{"filename":"0045.png","rotated":false,"trimmed":true,"sourceSize":{"w":98,"h":95},"spriteSourceSize":{"x":2,"y":0,"w":88,"h":95},"frame":{"x":264,"y":475,"w":88,"h":95}},{"filename":"0046.png","rotated":false,"trimmed":true,"sourceSize":{"w":98,"h":95},"spriteSourceSize":{"x":2,"y":0,"w":88,"h":95},"frame":{"x":352,"y":475,"w":88,"h":95}},{"filename":"0047.png","rotated":false,"trimmed":true,"sourceSize":{"w":98,"h":95},"spriteSourceSize":{"x":2,"y":0,"w":88,"h":95},"frame":{"x":0,"y":570,"w":88,"h":95}},{"filename":"0048.png","rotated":false,"trimmed":true,"sourceSize":{"w":98,"h":95},"spriteSourceSize":{"x":2,"y":0,"w":88,"h":95},"frame":{"x":88,"y":570,"w":88,"h":95}},{"filename":"0079.png","rotated":false,"trimmed":true,"sourceSize":{"w":98,"h":95},"spriteSourceSize":{"x":2,"y":0,"w":88,"h":95},"frame":{"x":176,"y":570,"w":88,"h":95}},{"filename":"0080.png","rotated":false,"trimmed":true,"sourceSize":{"w":98,"h":95},"spriteSourceSize":{"x":2,"y":0,"w":88,"h":95},"frame":{"x":264,"y":570,"w":88,"h":95}},{"filename":"0081.png","rotated":false,"trimmed":true,"sourceSize":{"w":98,"h":95},"spriteSourceSize":{"x":2,"y":0,"w":88,"h":95},"frame":{"x":352,"y":570,"w":88,"h":95}},{"filename":"0082.png","rotated":false,"trimmed":true,"sourceSize":{"w":98,"h":95},"spriteSourceSize":{"x":2,"y":0,"w":88,"h":95},"frame":{"x":0,"y":665,"w":88,"h":95}},{"filename":"0083.png","rotated":false,"trimmed":true,"sourceSize":{"w":98,"h":95},"spriteSourceSize":{"x":2,"y":0,"w":88,"h":95},"frame":{"x":88,"y":665,"w":88,"h":95}},{"filename":"0084.png","rotated":false,"trimmed":true,"sourceSize":{"w":98,"h":95},"spriteSourceSize":{"x":2,"y":0,"w":88,"h":95},"frame":{"x":176,"y":665,"w":88,"h":95}},{"filename":"0005.png","rotated":false,"trimmed":true,"sourceSize":{"w":98,"h":95},"spriteSourceSize":{"x":5,"y":0,"w":88,"h":95},"frame":{"x":264,"y":665,"w":88,"h":95}},{"filename":"0006.png","rotated":false,"trimmed":true,"sourceSize":{"w":98,"h":95},"spriteSourceSize":{"x":5,"y":0,"w":88,"h":95},"frame":{"x":352,"y":665,"w":88,"h":95}},{"filename":"0009.png","rotated":false,"trimmed":true,"sourceSize":{"w":98,"h":95},"spriteSourceSize":{"x":5,"y":0,"w":88,"h":95},"frame":{"x":0,"y":760,"w":88,"h":95}},{"filename":"0010.png","rotated":false,"trimmed":true,"sourceSize":{"w":98,"h":95},"spriteSourceSize":{"x":5,"y":0,"w":88,"h":95},"frame":{"x":88,"y":760,"w":88,"h":95}},{"filename":"0025.png","rotated":false,"trimmed":true,"sourceSize":{"w":98,"h":95},"spriteSourceSize":{"x":5,"y":0,"w":88,"h":95},"frame":{"x":176,"y":760,"w":88,"h":95}},{"filename":"0026.png","rotated":false,"trimmed":true,"sourceSize":{"w":98,"h":95},"spriteSourceSize":{"x":5,"y":0,"w":88,"h":95},"frame":{"x":264,"y":760,"w":88,"h":95}},{"filename":"0029.png","rotated":false,"trimmed":true,"sourceSize":{"w":98,"h":95},"spriteSourceSize":{"x":5,"y":0,"w":88,"h":95},"frame":{"x":352,"y":760,"w":88,"h":95}},{"filename":"0030.png","rotated":false,"trimmed":true,"sourceSize":{"w":98,"h":95},"spriteSourceSize":{"x":5,"y":0,"w":88,"h":95},"frame":{"x":0,"y":855,"w":88,"h":95}},{"filename":"0007.png","rotated":false,"trimmed":true,"sourceSize":{"w":98,"h":95},"spriteSourceSize":{"x":7,"y":0,"w":87,"h":95},"frame":{"x":88,"y":855,"w":87,"h":95}},{"filename":"0008.png","rotated":false,"trimmed":true,"sourceSize":{"w":98,"h":95},"spriteSourceSize":{"x":7,"y":0,"w":87,"h":95},"frame":{"x":175,"y":855,"w":87,"h":95}},{"filename":"0027.png","rotated":false,"trimmed":true,"sourceSize":{"w":98,"h":95},"spriteSourceSize":{"x":7,"y":0,"w":87,"h":95},"frame":{"x":262,"y":855,"w":87,"h":95}},{"filename":"0028.png","rotated":false,"trimmed":true,"sourceSize":{"w":98,"h":95},"spriteSourceSize":{"x":7,"y":0,"w":87,"h":95},"frame":{"x":349,"y":855,"w":87,"h":95}},{"filename":"0049.png","rotated":false,"trimmed":true,"sourceSize":{"w":98,"h":95},"spriteSourceSize":{"x":3,"y":1,"w":88,"h":94},"frame":{"x":0,"y":950,"w":88,"h":94}},{"filename":"0050.png","rotated":false,"trimmed":true,"sourceSize":{"w":98,"h":95},"spriteSourceSize":{"x":3,"y":1,"w":88,"h":94},"frame":{"x":88,"y":950,"w":88,"h":94}},{"filename":"0077.png","rotated":false,"trimmed":true,"sourceSize":{"w":98,"h":95},"spriteSourceSize":{"x":3,"y":1,"w":88,"h":94},"frame":{"x":176,"y":950,"w":88,"h":94}},{"filename":"0078.png","rotated":false,"trimmed":true,"sourceSize":{"w":98,"h":95},"spriteSourceSize":{"x":3,"y":1,"w":88,"h":94},"frame":{"x":264,"y":950,"w":88,"h":94}},{"filename":"0053.png","rotated":false,"trimmed":true,"sourceSize":{"w":98,"h":95},"spriteSourceSize":{"x":5,"y":3,"w":92,"h":92},"frame":{"x":352,"y":950,"w":92,"h":92}},{"filename":"0054.png","rotated":false,"trimmed":true,"sourceSize":{"w":98,"h":95},"spriteSourceSize":{"x":5,"y":3,"w":92,"h":92},"frame":{"x":0,"y":1044,"w":92,"h":92}},{"filename":"0073.png","rotated":false,"trimmed":true,"sourceSize":{"w":98,"h":95},"spriteSourceSize":{"x":5,"y":3,"w":92,"h":92},"frame":{"x":92,"y":1044,"w":92,"h":92}},{"filename":"0074.png","rotated":false,"trimmed":true,"sourceSize":{"w":98,"h":95},"spriteSourceSize":{"x":5,"y":3,"w":92,"h":92},"frame":{"x":184,"y":1044,"w":92,"h":92}},{"filename":"0017.png","rotated":false,"trimmed":true,"sourceSize":{"w":98,"h":95},"spriteSourceSize":{"x":0,"y":2,"w":90,"h":93},"frame":{"x":276,"y":1044,"w":90,"h":93}},{"filename":"0018.png","rotated":false,"trimmed":true,"sourceSize":{"w":98,"h":95},"spriteSourceSize":{"x":0,"y":2,"w":90,"h":93},"frame":{"x":366,"y":1044,"w":90,"h":93}},{"filename":"0037.png","rotated":false,"trimmed":true,"sourceSize":{"w":98,"h":95},"spriteSourceSize":{"x":0,"y":2,"w":90,"h":93},"frame":{"x":0,"y":1137,"w":90,"h":93}},{"filename":"0038.png","rotated":false,"trimmed":true,"sourceSize":{"w":98,"h":95},"spriteSourceSize":{"x":0,"y":2,"w":90,"h":93},"frame":{"x":90,"y":1137,"w":90,"h":93}},{"filename":"0055.png","rotated":false,"trimmed":true,"sourceSize":{"w":98,"h":95},"spriteSourceSize":{"x":6,"y":4,"w":92,"h":91},"frame":{"x":180,"y":1137,"w":92,"h":91}},{"filename":"0056.png","rotated":false,"trimmed":true,"sourceSize":{"w":98,"h":95},"spriteSourceSize":{"x":6,"y":4,"w":92,"h":91},"frame":{"x":272,"y":1137,"w":92,"h":91}},{"filename":"0059.png","rotated":false,"trimmed":true,"sourceSize":{"w":98,"h":95},"spriteSourceSize":{"x":6,"y":4,"w":92,"h":91},"frame":{"x":364,"y":1137,"w":92,"h":91}},{"filename":"0060.png","rotated":false,"trimmed":true,"sourceSize":{"w":98,"h":95},"spriteSourceSize":{"x":6,"y":4,"w":92,"h":91},"frame":{"x":0,"y":1230,"w":92,"h":91}},{"filename":"0063.png","rotated":false,"trimmed":true,"sourceSize":{"w":98,"h":95},"spriteSourceSize":{"x":6,"y":4,"w":92,"h":91},"frame":{"x":92,"y":1230,"w":92,"h":91}},{"filename":"0064.png","rotated":false,"trimmed":true,"sourceSize":{"w":98,"h":95},"spriteSourceSize":{"x":6,"y":4,"w":92,"h":91},"frame":{"x":184,"y":1230,"w":92,"h":91}},{"filename":"0067.png","rotated":false,"trimmed":true,"sourceSize":{"w":98,"h":95},"spriteSourceSize":{"x":6,"y":4,"w":92,"h":91},"frame":{"x":276,"y":1230,"w":92,"h":91}},{"filename":"0068.png","rotated":false,"trimmed":true,"sourceSize":{"w":98,"h":95},"spriteSourceSize":{"x":6,"y":4,"w":92,"h":91},"frame":{"x":368,"y":1230,"w":92,"h":91}},{"filename":"0071.png","rotated":false,"trimmed":true,"sourceSize":{"w":98,"h":95},"spriteSourceSize":{"x":6,"y":4,"w":92,"h":91},"frame":{"x":0,"y":1321,"w":92,"h":91}},{"filename":"0072.png","rotated":false,"trimmed":true,"sourceSize":{"w":98,"h":95},"spriteSourceSize":{"x":6,"y":4,"w":92,"h":91},"frame":{"x":92,"y":1321,"w":92,"h":91}},{"filename":"0051.png","rotated":false,"trimmed":true,"sourceSize":{"w":98,"h":95},"spriteSourceSize":{"x":3,"y":2,"w":90,"h":93},"frame":{"x":184,"y":1321,"w":90,"h":93}},{"filename":"0052.png","rotated":false,"trimmed":true,"sourceSize":{"w":98,"h":95},"spriteSourceSize":{"x":3,"y":2,"w":90,"h":93},"frame":{"x":274,"y":1321,"w":90,"h":93}},{"filename":"0075.png","rotated":false,"trimmed":true,"sourceSize":{"w":98,"h":95},"spriteSourceSize":{"x":3,"y":2,"w":90,"h":93},"frame":{"x":364,"y":1321,"w":90,"h":93}},{"filename":"0076.png","rotated":false,"trimmed":true,"sourceSize":{"w":98,"h":95},"spriteSourceSize":{"x":3,"y":2,"w":90,"h":93},"frame":{"x":0,"y":1414,"w":90,"h":93}},{"filename":"0057.png","rotated":false,"trimmed":true,"sourceSize":{"w":98,"h":95},"spriteSourceSize":{"x":6,"y":4,"w":92,"h":91},"frame":{"x":90,"y":1414,"w":92,"h":91}},{"filename":"0058.png","rotated":false,"trimmed":true,"sourceSize":{"w":98,"h":95},"spriteSourceSize":{"x":6,"y":4,"w":92,"h":91},"frame":{"x":182,"y":1414,"w":92,"h":91}},{"filename":"0065.png","rotated":false,"trimmed":true,"sourceSize":{"w":98,"h":95},"spriteSourceSize":{"x":6,"y":4,"w":92,"h":91},"frame":{"x":274,"y":1414,"w":92,"h":91}},{"filename":"0066.png","rotated":false,"trimmed":true,"sourceSize":{"w":98,"h":95},"spriteSourceSize":{"x":6,"y":4,"w":92,"h":91},"frame":{"x":366,"y":1414,"w":92,"h":91}},{"filename":"0061.png","rotated":false,"trimmed":true,"sourceSize":{"w":98,"h":95},"spriteSourceSize":{"x":6,"y":4,"w":92,"h":91},"frame":{"x":0,"y":1507,"w":92,"h":91}},{"filename":"0062.png","rotated":false,"trimmed":true,"sourceSize":{"w":98,"h":95},"spriteSourceSize":{"x":6,"y":4,"w":92,"h":91},"frame":{"x":92,"y":1507,"w":92,"h":91}},{"filename":"0069.png","rotated":false,"trimmed":true,"sourceSize":{"w":98,"h":95},"spriteSourceSize":{"x":6,"y":4,"w":92,"h":91},"frame":{"x":184,"y":1507,"w":92,"h":91}},{"filename":"0070.png","rotated":false,"trimmed":true,"sourceSize":{"w":98,"h":95},"spriteSourceSize":{"x":6,"y":4,"w":92,"h":91},"frame":{"x":276,"y":1507,"w":92,"h":91}}]}],"meta":{"app":"https://www.codeandweb.com/texturepacker","version":"3.0","smartupdate":"$TexturePacker:SmartUpdate:ef092b570a4bc097b8cae483e9cbe29d:6be5719b91e11641c18f4e6ac14c77b5:c66a2aabd1a8c5d889fdcc5e014ebb67$"}}